pytrimal/CMakeLists.txt
pytrimal/__init__.py
pytrimal/_trimal.cpython-39-aarch64-linux-gnu.so
pytrimal/_trimal.pxd
pytrimal/_trimal.pyi
pytrimal/_trimal.pyx
pytrimal/_version.py
pytrimal/py.typed
pytrimal/patch/omp.h
pytrimal/tests/__init__.py
pytrimal/tests/__main__.py
pytrimal/tests/_base.py
pytrimal/tests/requirements.txt
pytrimal/tests/test_alignment.py
pytrimal/tests/test_automatic_trimmer.py
pytrimal/tests/test_doctest.py
pytrimal/tests/test_manual_trimmer.py
pytrimal/tests/test_overlap_trimmer.py
pytrimal/tests/test_representative_trimmer.py
pytrimal/tests/test_similarity_matrix.py
pytrimal/tests/data/ENOG411BWBU.automated1.fasta
pytrimal/tests/data/ENOG411BWBU.automated2.fasta
pytrimal/tests/data/ENOG411BWBU.clusters10.fasta
pytrimal/tests/data/ENOG411BWBU.clusters5.fasta
pytrimal/tests/data/ENOG411BWBU.cons40.gt40.fasta
pytrimal/tests/data/ENOG411BWBU.cons60.gt90.fasta
pytrimal/tests/data/ENOG411BWBU.fasta
pytrimal/tests/data/ENOG411BWBU.gappyout.fasta
pytrimal/tests/data/ENOG411BWBU.id50.fasta
pytrimal/tests/data/ENOG411BWBU.id70.fasta
pytrimal/tests/data/ENOG411BWBU.maxidentity75.fasta
pytrimal/tests/data/ENOG411BWBU.noallgaps.fasta
pytrimal/tests/data/ENOG411BWBU.noduplicateseqs.fasta
pytrimal/tests/data/ENOG411BWBU.seq40.res60.fasta
pytrimal/tests/data/ENOG411BWBU.seq80.res80.fasta
pytrimal/tests/data/ENOG411BWBU.strict.fasta
pytrimal/tests/data/ENOG411BWBU.strictplus.fasta
pytrimal/tests/data/PF12574.full.afa
pytrimal/tests/data/__init__.py
pytrimal/tests/data/example.001.AA.clw
pytrimal/tests/data/example.001.gt90.w3.clw
pytrimal/tests/data/halorhodopsin.afa
pytrimal/tests/data/pam70.json
pytrimal-0.8.4.dist-info/METADATA
pytrimal-0.8.4.dist-info/WHEEL
pytrimal-0.8.4.dist-info/RECORD
pytrimal-0.8.4.dist-info/licenses/COPYING
