Metadata-Version: 2.1
Name: pytrimal
Version: 0.8.4
Summary: Cython bindings and Python interface to trimAl, a tool for automated alignment trimming.
Keywords: bioinformatics,sequence,alignment,trimming,genomics
License:                     GNU GENERAL PUBLIC LICENSE
Classifier: Development Status :: 4 - Beta
Classifier: Intended Audience :: Developers
Classifier: Intended Audience :: Science/Research
Classifier: License :: OSI Approved :: GNU General Public License v3 (GPLv3)
Classifier: Operating System :: OS Independent
Classifier: Programming Language :: C
Classifier: Programming Language :: Cython
Classifier: Programming Language :: Python :: 3.6
Classifier: Programming Language :: Python :: 3.7
Classifier: Programming Language :: Python :: 3.8
Classifier: Programming Language :: Python :: 3.9
Classifier: Programming Language :: Python :: 3.10
Classifier: Programming Language :: Python :: 3.11
Classifier: Programming Language :: Python :: 3.12
Classifier: Programming Language :: Python :: 3.13
Classifier: Programming Language :: Python :: Implementation :: CPython
Classifier: Programming Language :: Python :: Implementation :: PyPy
Classifier: Topic :: Scientific/Engineering :: Bio-Informatics
Classifier: Topic :: Scientific/Engineering :: Medical Science Apps.
Classifier: Typing :: Typed
Project-URL: Documentation, https://pytrimal.readthedocs.io/en/stable/
Project-URL: Bug tracker, https://github.com/althonos/pytrimal/issues
Project-URL: Changelog, https://github.com/althonos/pytrimal/blob/main/CHANGELOG.md
Project-URL: Coverage, https://codecov.io/gh/althonos/pytrimal/
Project-URL: Builds, https://github.com/althonos/pytrimal/actions
Project-URL: Pypi, https://pypi.org/project/pytrimal
Project-URL: Piwheels, https://piwheels.org/project/pytrimal
Requires-Python: >=3.7
Requires-Dist: scoring-matrices~=0.3.0
Requires-Dist: importlib-resources; python_version < "3.9" and extra == "test"
Provides-Extra: test
